{
  "Law": {
    "@Era": "Showa",
    "@Lang": "ja",
    "@LawType": "Act",
    "@Num": "89",
    "@Year": "50",
    "LawNum": "昭和五十年法律第八十九号",
    "LawBody": {
      "LawTitle": "昭和五十年度の公債の発行の特例に関する法律",
      "MainProvision": {
        "Article": [
          {
            "@Delete": "false",
            "@Hide": "false",
            "@Num": "1",
            "ArticleCaption": "（特例公債の発行）",
            "ArticleTitle": "第一条",
            "Paragraph": {
              "@Hide": "false",
              "@Num": "1",
              "ParagraphNum": null,
              "ParagraphSentence": {
                "Sentence": {
                  "@WritingMode": "vertical",
                  "#text": "政府は、財政法（昭和二十二年法律第三十四号）第四条第一項の規定にかかわらず、昭和五十年度の一般会計補正予算において見込まれる租税及び印紙収入並びに専売納付金の減少を補うため、当該補正予算をもつて国会の議決を経た金額の範囲内で、公債を発行することができる。"
                }
              }
            }
          },
          {
            "@Delete": "false",
            "@Hide": "false",
            "@Num": "2",
            "ArticleCaption": "（特例公債に係る発行時期及び会計年度所属区分の特例）",
            "ArticleTitle": "第二条",
            "Paragraph": {
              "@Hide": "false",
              "@Num": "1",
              "ParagraphNum": null,
              "ParagraphSentence": {
                "Sentence": [
                  {
                    "@Num": "1",
                    "@WritingMode": "vertical",
                    "#text": "前条の規定による公債の発行は、昭和五十一年五月三十一日までの間、行うことができる。"
                  },
                  {
                    "@Num": "2",
                    "@WritingMode": "vertical",
                    "#text": "この場合において、同年四月一日以後発行される同条の公債に係る収入は、昭和五十年度所属の歳入とする。"
                  }
                ]
              }
            }
          },
          {
            "@Delete": "false",
            "@Hide": "false",
            "@Num": "3",
            "ArticleCaption": "（償還計画の国会への提出）",
            "ArticleTitle": "第三条",
            "Paragraph": {
              "@Hide": "false",
              "@Num": "1",
              "ParagraphNum": null,
              "ParagraphSentence": {
                "Sentence": {
                  "@WritingMode": "vertical",
                  "#text": "政府は、第一条の議決を経ようとするときは、同条の公債の償還の計画を国会に提出しなければならない。"
                }
              }
            }
          }
        ]
      },
      "SupplProvision": {
        "@Extract": "true",
        "@Type": "New",
        "SupplProvisionLabel": "附　則",
        "Paragraph": {
          "@Hide": "false",
          "@Num": "1",
          "ParagraphNum": "１",
          "ParagraphSentence": {
            "Sentence": {
              "@WritingMode": "vertical",
              "#text": "この法律は、公布の日から施行する。"
            }
          }
        }
      }
    }
  }
}
